{"nb_repos": 3972, "nb_orgs": 311, "avg_nb_repos": 12.77, "median_nb_repos": 2.0, "top_orgs_by_repos": [{"plateforme": "GitHub", "organisation_nom": "betagouv", "count": 267}, {"plateforme": "GitHub", "organisation_nom": "etalab", "count": 253}, {"plateforme": "GitHub", "organisation_nom": "medialab", "count": 169}, {"plateforme": "GitHub", "organisation_nom": "lutece-secteur-public", "count": 129}, {"plateforme": "GitHub", "organisation_nom": "SocialGouv", "count": 111}, {"plateforme": "GitHub", "organisation_nom": "clipos-archive", "count": 106}, {"plateforme": "GitHub", "organisation_nom": "EsupPortail", "count": 104}, {"plateforme": "GitHub", "organisation_nom": "entrepreneur-interet-general", "count": 86}, {"plateforme": "GitHub", "organisation_nom": "MTES-MCT", "count": 86}, {"plateforme": "GitHub", "organisation_nom": "Inist-CNRS", "count": 85}], "top_orgs_by_stars": {"cea-sec": 4540, "ANSSI-FR": 3164, "medialab": 2497, "etalab": 1775, "INRIA": 1450, "LINCnil": 1385, "OpenCTI-Platform": 1315, "betagouv": 1122, "cea-hpc": 887, "DISIC": 629}, "top_repos_stars": {"https://github.com/cea-sec/miasm": 2154, "https://github.com/cea-sec/ivre": 1848, "https://github.com/OpenCTI-Platform/opencti": 1246, "https://github.com/medialab/artoo": 1000, "https://github.com/INRIA/spoon": 942, "https://github.com/LINCnil/Guide-RGPD-du-developpeur": 746, "https://github.com/DIVERSIFY-project/amiunique": 569, "https://github.com/LAB-MI/deplacement-covid-19": 533, "https://github.com/medialab/iwanthue": 478, "https://github.com/ANSSI-FR/AD-control-paths": 455}, "top_repos_forks": {"https://github.com/cea-sec/ivre": 486, "https://github.com/betagouv/beta.gouv.fr": 364, "https://github.com/cea-sec/miasm": 355, "https://github.com/LINCnil/pia": 227, "https://github.com/OpenCTI-Platform/opencti": 219, "https://github.com/INRIA/spoon": 201, "https://github.com/LAB-MI/deplacement-covid-19": 189, "https://github.com/betagouv/api.gouv.fr": 108, "https://github.com/OCSInventory-NG/OCSInventory-ocsreports": 104, "https://github.com/micmacIGN/micmac": 92}, "top_repos_issues": {"https://gitlab.inria.fr/vidjil/vidjil": 1604, "https://github.com/betagouv/pass-culture-browser": 383, "https://github.com/betagouv/demarches-simplifiees.fr": 286, "https://github.com/PnX-SI/GeoNature": 283, "https://forgemia.inra.fr/metexplore/metexplore2": 252, "https://gitlab.orfeo-toolbox.org/orfeotoolbox/otb": 240, "https://gitlab.ow2.org/lemonldap-ng/lemonldap-ng": 238, "https://framagit.org/etalab/suivi": 211, "https://github.com/DISIC/wikidemarches": 184, "https://github.com/entrepreneur-interet-general/CIS-front": 157}, "top_licenses": {"Inconnue": 2057, "MIT License": 464, "Other": 380, "GNU Affero General Public License v3.0": 257, "GNU General Public License v3.0": 241, "Apache License 2.0": 155, "GNU Lesser General Public License v2.1": 126, "BSD 3-Clause \"New\" or \"Revised\" License": 85, "GNU General Public License v2.0": 71, "GNU Lesser General Public License v3.0": 42, "Eclipse Public License 2.0": 27, "Mozilla Public License 2.0": 24, "European Union Public License 1.2": 13, "Eclipse Public License 1.0": 12, "Creative Commons Attribution Share Alike 4.0 International": 7, "BSD 2-Clause \"Simplified\" License": 5, "Creative Commons Attribution 4.0 International": 2, "The Unlicense": 2, "Do What The Fuck You Want To Public License": 1, "Creative Commons Zero v1.0 Universal": 1}, "top_languages": {"Inconnu": 999, "JavaScript": 722, "Python": 486, "Java": 370, "HTML": 238, "Shell": 177, "C": 124, "CSS": 104, "PHP": 91, "Ruby": 82, "TypeScript": 70}, "platforms": {"GitHub": 3417, "GitLab": 555}, "software_heritage": {"repos_in_archive": 3956, "ratio_in_archive": 1.0}}