{"nb_repos": 3589, "nb_orgs": 284, "avg_nb_repos": 12.64, "median_nb_repos": 2.0, "top_orgs_by_repos": [{"plateforme": "GitHub", "organisation_nom": "betagouv", "count": 253}, {"plateforme": "GitHub", "organisation_nom": "etalab", "count": 243}, {"plateforme": "GitHub", "organisation_nom": "medialab", "count": 166}, {"plateforme": "GitHub", "organisation_nom": "lutece-secteur-public", "count": 127}, {"plateforme": "GitHub", "organisation_nom": "SocialGouv", "count": 111}, {"plateforme": "GitHub", "organisation_nom": "clipos-archive", "count": 106}, {"plateforme": "GitHub", "organisation_nom": "entrepreneur-interet-general", "count": 86}, {"plateforme": "GitHub", "organisation_nom": "MTES-MCT", "count": 85}, {"plateforme": "GitHub", "organisation_nom": "Inist-CNRS", "count": 84}, {"plateforme": "GitHub", "organisation_nom": "openfun", "count": 72}], "top_orgs_by_stars": {"cea-sec": 4381, "ANSSI-FR": 3019, "medialab": 2421, "etalab": 1640, "INRIA": 1395, "LINCnil": 1188, "OpenCTI-Platform": 1156, "betagouv": 1151, "cea-hpc": 831, "DISIC": 612}, "top_repos_stars": {"https://github.com/cea-sec/miasm": 2079, "https://github.com/cea-sec/ivre": 1777, "https://github.com/OpenCTI-Platform/opencti": 1103, "https://github.com/medialab/artoo": 990, "https://github.com/INRIA/spoon": 912, "https://github.com/LINCnil/Guide-RGPD-du-developpeur": 694, "https://github.com/DIVERSIFY-project/amiunique": 563, "https://github.com/medialab/iwanthue": 462, "https://github.com/ANSSI-FR/AD-control-paths": 449, "https://github.com/cea-sec/Sibyl": 419}, "top_repos_forks": {"https://github.com/cea-sec/ivre": 477, "https://github.com/cea-sec/miasm": 346, "https://github.com/betagouv/beta.gouv.fr": 346, "https://github.com/LINCnil/pia": 220, "https://github.com/INRIA/spoon": 193, "https://github.com/OpenCTI-Platform/opencti": 180, "https://github.com/LAB-MI/deplacement-covid-19": 126, "https://github.com/betagouv/api.gouv.fr": 105, "https://github.com/OCSInventory-NG/OCSInventory-ocsreports": 102, "https://github.com/micmacIGN/micmac": 88}, "top_repos_issues": {"https://gitlab.inria.fr/vidjil/vidjil": 1512, "https://github.com/betagouv/pass-culture-browser": 379, "https://github.com/betagouv/demarches-simplifiees.fr": 278, "https://forgemia.inra.fr/metexplore/metexplore2": 257, "https://github.com/PnX-SI/GeoNature": 255, "https://gitlab.ow2.org/lemonldap-ng/lemonldap-ng": 229, "https://framagit.org/etalab/suivi": 211, "https://github.com/DISIC/wikidemarches": 180, "https://github.com/SocialGouv/code-du-travail-numerique": 167, "https://github.com/entrepreneur-interet-general/CIS-front": 157}, "top_licenses": {"Inconnue": 1872, "MIT License": 422, "Other": 358, "GNU Affero General Public License v3.0": 258, "GNU General Public License v3.0": 237, "GNU Lesser General Public License v2.1": 126, "Apache License 2.0": 106, "GNU General Public License v2.0": 68, "GNU Lesser General Public License v3.0": 39, "Mozilla Public License 2.0": 24, "Eclipse Public License 2.0": 23, "BSD 3-Clause \"New\" or \"Revised\" License": 14, "European Union Public License 1.2": 12, "Eclipse Public License 1.0": 12, "Creative Commons Attribution Share Alike 4.0 International": 7, "BSD 2-Clause \"Simplified\" License": 5, "Creative Commons Attribution 4.0 International": 2, "The Unlicense": 2, "Do What The Fuck You Want To Public License": 1, "Creative Commons Zero v1.0 Universal": 1}, "top_languages": {"Inconnu": 854, "JavaScript": 686, "Python": 435, "Java": 311, "HTML": 232, "Shell": 159, "C": 114, "CSS": 100, "PHP": 86, "Ruby": 79, "TypeScript": 65}, "platforms": {"GitHub": 3151, "GitLab": 438}, "software_heritage": {"repos_in_archive": 3585, "ratio_in_archive": 1.0}}