{"nb_repos": 3669, "nb_orgs": 407, "avg_nb_repos": 9.01, "median_nb_repos": 2.0, "top_orgs_by_repos": [{"plateforme": "GitHub", "organisation_nom": "etalab", "count": 223}, {"plateforme": "GitHub", "organisation_nom": "betagouv", "count": 219}, {"plateforme": "GitHub", "organisation_nom": "medialab", "count": 157}, {"plateforme": "GitHub", "organisation_nom": "lutece-secteur-public", "count": 122}, {"plateforme": "GitHub", "organisation_nom": "clipos-archive", "count": 106}, {"plateforme": "GitHub", "organisation_nom": "SocialGouv", "count": 84}, {"plateforme": "GitHub", "organisation_nom": "entrepreneur-interet-general", "count": 83}, {"plateforme": "GitHub", "organisation_nom": "Inist-CNRS", "count": 81}, {"plateforme": "GitHub", "organisation_nom": "unistra", "count": 64}, {"plateforme": "GitHub", "organisation_nom": "openfun", "count": 64}], "top_orgs_by_stars": {"cea-sec": 4044, "ANSSI-FR": 2621, "medialab": 2284, "etalab": 1356, "INRIA": 1240, "OpenCTI-Platform": 860, "betagouv": 847, "cea-hpc": 752, "DISIC": 591, "DIVERSIFY-project": 583}, "top_repos_stars": {"https://github.com/cea-sec/miasm": 1910, "https://github.com/cea-sec/ivre": 1631, "https://github.com/medialab/artoo": 963, "https://github.com/INRIA/spoon": 840, "https://github.com/OpenCTI-Platform/opencti": 839, "https://github.com/DIVERSIFY-project/amiunique": 540, "https://github.com/medialab/iwanthue": 439, "https://github.com/ANSSI-FR/AD-control-paths": 399, "https://github.com/cea-sec/Sibyl": 399, "https://github.com/ANSSI-FR/rust-guide": 277}, "top_repos_forks": {"https://github.com/cea-sec/ivre": 440, "https://github.com/cea-sec/miasm": 322, "https://github.com/betagouv/beta.gouv.fr": 290, "https://github.com/LINCnil/pia": 196, "https://github.com/INRIA/spoon": 163, "https://github.com/OpenCTI-Platform/opencti": 115, "https://github.com/OCSInventory-NG/OCSInventory-ocsreports": 98, "https://github.com/betagouv/api.gouv.fr": 85, "https://github.com/DIVERSIFY-project/amiunique": 84, "https://github.com/openfisca/openfisca-france": 82}, "top_repos_issues": {"https://gitlab.inria.fr/vidjil/vidjil": 1401, "https://github.com/betagouv/demarches-simplifiees.fr": 884, "https://github.com/betagouv/pass-culture-browser": 380, "https://gitlab.inria.fr/allgo/allgo": 254, "https://framagit.org/etalab/suivi": 211, "https://github.com/PnX-SI/GeoNature": 202, "https://gitlab.ow2.org/lemonldap-ng/lemonldap-ng": 193, "https://github.com/SocialGouv/code-du-travail-numerique": 168, "https://github.com/entrepreneur-interet-general/CIS-front": 157, "https://github.com/betagouv/mon-entreprise": 140}, "top_licenses": {"Inconnue": 2141, "MIT License": 362, "Other": 320, "GNU Affero General Public License v3.0": 237, "GNU General Public License v3.0": 196, "GNU Lesser General Public License v2.1": 126, "Apache License 2.0": 92, "GNU General Public License v2.0": 69, "GNU Lesser General Public License v3.0": 34, "Mozilla Public License 2.0": 23, "Eclipse Public License 2.0": 18, "Eclipse Public License 1.0": 13, "BSD 3-Clause \"New\" or \"Revised\" License": 12, "European Union Public License 1.2": 11, "Creative Commons Attribution Share Alike 4.0 International": 7, "BSD 2-Clause \"Simplified\" License": 4, "The Unlicense": 2, "Do What The Fuck You Want To Public License": 1, "Creative Commons Attribution 4.0 International": 1}, "top_languages": {"Inconnu": 1213, "JavaScript": 629, "Python": 405, "Java": 303, "HTML": 193, "Shell": 142, "C": 104, "CSS": 94, "PHP": 77, "Ruby": 74}, "platforms": {"GitHub": 2817, "GitLab": 852}, "software_heritage": {"repos_in_archive": 3486, "ratio_in_archive": 0.95}}